phaseq/__init__.py
phaseq/main.py
phaseq/py.typed
phaseq-0.0.2.dev1.dist-info/METADATA
phaseq-0.0.2.dev1.dist-info/WHEEL
phaseq-0.0.2.dev1.dist-info/RECORD
