Metadata-Version: 2.4
Name: phaseq
Version: 0.0.2.dev1
Summary: Add your description here
Author-email: Ivan Antolovic <62339319+ivanantolo@users.noreply.github.com>
Requires-Python: >=3.12
Requires-Dist: click>=8.1.8
Requires-Dist: numpy>=2.2.5
Requires-Dist: pandas>=2.2.3
